{
  "resourceType": "StructureDefinition",
  "id": "access-restriction-range",
  "url": "http://hl7.org/fhir/v2-tofhir/StructureDefinition/access-restriction-range",
  "version": "0.1.0",
  "name": "AccessRestrictionRange",
  "status": "active",
  "description": "The Access Restriction Date Range. This extension corresponds to ARV-6 of the original message.",
  "fhirVersion": "4.0.1",
  "mapping": [
    {
      "identity": "rim",
      "uri": "http://hl7.org/v3",
      "name": "RIM Mapping"
    }
  ],
  "kind": "complex-type",
  "abstract": false,
  "context": [
    {
      "type": "element",
      "expression": "meta.security"
    }
  ],
  "type": "Extension",
  "baseDefinition": "http://hl7.org/fhir/StructureDefinition/Extension",
  "derivation": "constraint",
  "differential": {
    "element": [
      {
        "id": "Extension.extension",
        "path": "Extension.extension",
        "max": "0"
      },
      {
        "id": "Extension.url",
        "path": "Extension.url",
        "fixedUri": "http://hl7.org/fhir/v2-tofhir/StructureDefinition/access-restriction-range"
      },
      {
        "id": "Extension.value[x]",
        "path": "Extension.value[x]",
        "slicing": {
          "discriminator": [
            {
              "type": "type",
              "path": "$this"
            }
          ],
          "ordered": false,
          "rules": "open"
        },
        "min": 1,
        "type": [
          {
            "code": "Period"
          }
        ]
      },
      {
        "id": "Extension.valuePeriod",
        "path": "Extension.valuePeriod",
        "min": 1,
        "max": "1"
      }
    ]
  }
}
