{
  "resourceType": "ConceptMap",
  "id": "segment-rolpv1-pv2-practitionerrole-to-encounter",
  "description": "This ConceptMap represents the mapping from the HL7 V2 ROL Segment to the FHIR Encounter Resource.",
  "url": "http://hl7.org/fhir/v2-tofhir/segment-rolpv1-pv2-practitionerrole-to-encounter",
  "version": "1.0",
  "name": "Segment_ROL_Map",
  "status": "active",
  "experimental": true,
  "date": "2020-07-30",
  "publisher": "HL7 International, Inc",
  "contact": [
    {
      "telecom": [
        {
          "system": "email",
          "value": "v2-to-fhir@lists.hl7.org"
        }
      ]
    }
  ],
  "copyright": "Copyright (c) 2020, HL7 International, Inc., All Rights Reserved.",
  "sourceUri": "ROL",
  "targetUri": "Encounter",
  "extension": [
    {
      "url": "http://hl7.org/fhir/v2-tofhir/StructureDefinition/RelatedArtifact",
      "extension": [
        {
          "url": "type",
          "valueCode": "derived-from"
        },
        {
          "url": "label",
          "valueString": "Segment ROL[PV1-PV2-PractitionerRole] to Encounter.fsh"
        },
        {
          "url": "url",
          "valueUri": "https://docs.google.com/spreadsheets/d/17J53J2VmqnNff7s3Yi2RQceWvdy6vagJTTsQo7kxuG0/edit#gid=0"
        }
      ]
    }
  ],
  "group": [
    {
      "element": [
        {
          "code": "ROL-1",
          "extension": [
            {
              "url": "http://hl7.org/fhir/v2-tofhir/StructureDefinition/TypeInfo",
              "extension": [
                {
                  "url": "type",
                  "valueCode": "EI"
                },
                {
                  "url": "cardinalityMin",
                  "valueInteger": 1
                },
                {
                  "url": "cardinalityMax",
                  "valueInteger": 1
                }
              ]
            }
          ],
          "display": "Role Instance ID",
          "target": [
            {
              "equivalence": "equivalent",
              "code": "Encounter[PV1].participant[1].individual.reference",
              "extension": [
                {
                  "url": "http://hl7.org/fhir/v2-tofhir/StructureDefinition/TypeInfo",
                  "extension": [
                    {
                      "url": "type",
                      "valueCode": "identifier"
                    },
                    {
                      "url": "cardinalityMin",
                      "valueInteger": 0
                    },
                    {
                      "url": "cardinalityMax",
                      "valueInteger": -1
                    }
                  ]
                }
              ],
              "display": "Encounter[PV1].participant[1].individual.reference",
              "dependsOn": [
                {
                  "property": "data-type-map",
                  "value": "EI[Identifier]"
                }
              ]
            }
          ]
        },
        {
          "code": "ROL-1",
          "extension": [
            {
              "url": "http://hl7.org/fhir/v2-tofhir/StructureDefinition/TypeInfo",
              "extension": [
                {
                  "url": "type",
                  "valueCode": "EI"
                },
                {
                  "url": "cardinalityMin",
                  "valueInteger": 1
                },
                {
                  "url": "cardinalityMax",
                  "valueInteger": 1
                }
              ]
            }
          ],
          "display": "Role Instance ID",
          "target": [
            {
              "equivalence": "equivalent",
              "code": "Encounter[PV1].participant[1].individual[1](PractitionerRole.identifier)",
              "display": "Encounter[PV1].participant[1].individual[1](PractitionerRole.identifier)"
            }
          ]
        },
        {
          "code": "ROL-2",
          "extension": [
            {
              "url": "http://hl7.org/fhir/v2-tofhir/StructureDefinition/TypeInfo",
              "extension": [
                {
                  "url": "type",
                  "valueCode": "ID"
                },
                {
                  "url": "cardinalityMin",
                  "valueInteger": 1
                },
                {
                  "url": "cardinalityMax",
                  "valueInteger": 1
                }
              ]
            }
          ],
          "display": "Action Code",
          "target": [
            {
              "equivalence": "equivalent",
              "code": "Operation",
              "display": "Operation",
              "dependsOn": [
                {
                  "property": "vocabulary-map",
                  "value": "Operation"
                }
              ],
              "product": [
                {
                  "property": "narrative",
                  "value": "if mapped to a restful service to progress the message."
                }
              ]
            }
          ]
        },
        {
          "code": "ROL-3",
          "extension": [
            {
              "url": "http://hl7.org/fhir/v2-tofhir/StructureDefinition/TypeInfo",
              "extension": [
                {
                  "url": "type",
                  "valueCode": "CWE"
                },
                {
                  "url": "cardinalityMin",
                  "valueInteger": 1
                },
                {
                  "url": "cardinalityMax",
                  "valueInteger": 1
                }
              ]
            }
          ],
          "display": "Role-ROL",
          "target": [
            {
              "equivalence": "equivalent",
              "code": "Encounter[PV1].participant[1].type",
              "extension": [
                {
                  "url": "http://hl7.org/fhir/v2-tofhir/StructureDefinition/TypeInfo",
                  "extension": [
                    {
                      "url": "type",
                      "valueCode": "CodeableConcept"
                    },
                    {
                      "url": "cardinalityMin",
                      "valueInteger": 0
                    },
                    {
                      "url": "cardinalityMax",
                      "valueInteger": -1
                    }
                  ]
                }
              ],
              "display": "Encounter[PV1].participant[1].type",
              "dependsOn": [
                {
                  "property": "data-type-map",
                  "value": "CWE[CodeableConcept]"
                },
                {
                  "property": "vocabulary-map",
                  "value": "Role"
                }
              ]
            }
          ]
        },
        {
          "code": "ROL-4",
          "extension": [
            {
              "url": "http://hl7.org/fhir/v2-tofhir/StructureDefinition/TypeInfo",
              "extension": [
                {
                  "url": "type",
                  "valueCode": "XCN"
                },
                {
                  "url": "cardinalityMin",
                  "valueInteger": -1
                },
                {
                  "url": "cardinalityMax",
                  "valueInteger": -1
                }
              ]
            }
          ],
          "display": "Role Person",
          "target": [
            {
              "equivalence": "equivalent",
              "code": "Encounter[PV1].participant[1].individual(PractitionerRole.practitioner)",
              "extension": [
                {
                  "url": "http://hl7.org/fhir/v2-tofhir/StructureDefinition/TypeInfo",
                  "extension": [
                    {
                      "url": "type",
                      "valueCode": "Reference(Practioner)"
                    }
                  ]
                }
              ],
              "display": "Encounter[PV1].participant[1].individual(PractitionerRole.practitioner)",
              "dependsOn": [
                {
                  "property": "data-type-map",
                  "value": "XCN[Practitioner]"
                }
              ]
            }
          ]
        },
        {
          "code": "ROL-5",
          "extension": [
            {
              "url": "http://hl7.org/fhir/v2-tofhir/StructureDefinition/TypeInfo",
              "extension": [
                {
                  "url": "type",
                  "valueCode": "DTM"
                },
                {
                  "url": "cardinalityMin",
                  "valueInteger": 1
                },
                {
                  "url": "cardinalityMax",
                  "valueInteger": 1
                }
              ]
            }
          ],
          "display": "Role Begin Date/Time",
          "target": [
            {
              "equivalence": "equivalent",
              "code": "Encounter[PV1].participant[1].period.start",
              "extension": [
                {
                  "url": "http://hl7.org/fhir/v2-tofhir/StructureDefinition/TypeInfo",
                  "extension": [
                    {
                      "url": "type",
                      "valueCode": "dateTime"
                    },
                    {
                      "url": "cardinalityMin",
                      "valueInteger": 0
                    },
                    {
                      "url": "cardinalityMax",
                      "valueInteger": 1
                    }
                  ]
                }
              ],
              "display": "Encounter[PV1].participant[1].period.start",
              "dependsOn": [
                {
                  "property": "data-type-map",
                  "value": "DTM"
                }
              ]
            }
          ]
        },
        {
          "code": "ROL-6",
          "extension": [
            {
              "url": "http://hl7.org/fhir/v2-tofhir/StructureDefinition/TypeInfo",
              "extension": [
                {
                  "url": "type",
                  "valueCode": "DTM"
                },
                {
                  "url": "cardinalityMin",
                  "valueInteger": 1
                },
                {
                  "url": "cardinalityMax",
                  "valueInteger": 1
                }
              ]
            }
          ],
          "display": "Role End Date/Time",
          "target": [
            {
              "equivalence": "equivalent",
              "code": "Encounter[PV1].participant[1].period.end",
              "extension": [
                {
                  "url": "http://hl7.org/fhir/v2-tofhir/StructureDefinition/TypeInfo",
                  "extension": [
                    {
                      "url": "type",
                      "valueCode": "dateTime"
                    },
                    {
                      "url": "cardinalityMin",
                      "valueInteger": 0
                    },
                    {
                      "url": "cardinalityMax",
                      "valueInteger": 1
                    }
                  ]
                }
              ],
              "display": "Encounter[PV1].participant[1].period.end",
              "dependsOn": [
                {
                  "property": "data-type-map",
                  "value": "DTM"
                }
              ]
            }
          ]
        },
        {
          "code": "ROL-11",
          "extension": [
            {
              "url": "http://hl7.org/fhir/v2-tofhir/StructureDefinition/TypeInfo",
              "extension": [
                {
                  "url": "type",
                  "valueCode": "XAD"
                },
                {
                  "url": "cardinalityMin",
                  "valueInteger": -1
                },
                {
                  "url": "cardinalityMax",
                  "valueInteger": -1
                }
              ]
            }
          ],
          "display": "Office/Home Address/Birthplace",
          "target": [
            {
              "equivalence": "equivalent",
              "code": "Encounter[PV1].participant[1].individual(PractitionerRole.practioner(Practitioner.address))",
              "extension": [
                {
                  "url": "http://hl7.org/fhir/v2-tofhir/StructureDefinition/TypeInfo",
                  "extension": [
                    {
                      "url": "type",
                      "valueCode": "Address"
                    },
                    {
                      "url": "cardinalityMin",
                      "valueInteger": 0
                    },
                    {
                      "url": "cardinalityMax",
                      "valueInteger": -1
                    }
                  ]
                }
              ],
              "display": "Encounter[PV1].participant[1].individual(PractitionerRole.practioner(Practitioner.address))",
              "dependsOn": [
                {
                  "property": "data-type-map",
                  "value": "XAD"
                }
              ]
            }
          ]
        },
        {
          "code": "ROL-12",
          "extension": [
            {
              "url": "http://hl7.org/fhir/v2-tofhir/StructureDefinition/TypeInfo",
              "extension": [
                {
                  "url": "type",
                  "valueCode": "XTN"
                },
                {
                  "url": "cardinalityMin",
                  "valueInteger": -1
                },
                {
                  "url": "cardinalityMax",
                  "valueInteger": -1
                }
              ]
            }
          ],
          "display": "Phone",
          "target": [
            {
              "equivalence": "equivalent",
              "code": "Encounter[PV1].participant[1].individual(PractitionerRole.telecom)",
              "extension": [
                {
                  "url": "http://hl7.org/fhir/v2-tofhir/StructureDefinition/TypeInfo",
                  "extension": [
                    {
                      "url": "type",
                      "valueCode": "ContactPoint"
                    },
                    {
                      "url": "cardinalityMin",
                      "valueInteger": 0
                    },
                    {
                      "url": "cardinalityMax",
                      "valueInteger": -1
                    }
                  ]
                }
              ],
              "display": "Encounter[PV1].participant[1].individual(PractitionerRole.telecom)",
              "dependsOn": [
                {
                  "property": "data-type-map",
                  "value": "XTN"
                }
              ]
            }
          ]
        },
        {
          "code": "ROL-13",
          "extension": [
            {
              "url": "http://hl7.org/fhir/v2-tofhir/StructureDefinition/TypeInfo",
              "extension": [
                {
                  "url": "type",
                  "valueCode": "PL"
                },
                {
                  "url": "cardinalityMin",
                  "valueInteger": 1
                },
                {
                  "url": "cardinalityMax",
                  "valueInteger": 1
                }
              ]
            }
          ],
          "display": "Person's Location",
          "target": [
            {
              "equivalence": "equivalent",
              "code": "Encounter[PV1].participant[1].individual(PractitionerRole.location(Location))",
              "extension": [
                {
                  "url": "http://hl7.org/fhir/v2-tofhir/StructureDefinition/TypeInfo",
                  "extension": [
                    {
                      "url": "type",
                      "valueCode": "Reference(Location)"
                    },
                    {
                      "url": "cardinalityMin",
                      "valueInteger": 0
                    },
                    {
                      "url": "cardinalityMax",
                      "valueInteger": 1
                    }
                  ]
                }
              ],
              "display": "Encounter[PV1].participant[1].individual(PractitionerRole.location(Location))",
              "dependsOn": [
                {
                  "property": "data-type-map",
                  "value": "PL"
                }
              ]
            }
          ]
        },
        {
          "code": "ROL-14",
          "extension": [
            {
              "url": "http://hl7.org/fhir/v2-tofhir/StructureDefinition/TypeInfo",
              "extension": [
                {
                  "url": "type",
                  "valueCode": "XON"
                },
                {
                  "url": "cardinalityMin",
                  "valueInteger": 1
                },
                {
                  "url": "cardinalityMax",
                  "valueInteger": 1
                }
              ]
            }
          ],
          "display": "Organization",
          "target": [
            {
              "equivalence": "equivalent",
              "code": "Encounter[PV1].participant[1].individual(PractitionerRole.organziation.(Organization))",
              "extension": [
                {
                  "url": "http://hl7.org/fhir/v2-tofhir/StructureDefinition/TypeInfo",
                  "extension": [
                    {
                      "url": "type",
                      "valueCode": "Reference(Organization)"
                    },
                    {
                      "url": "cardinalityMin",
                      "valueInteger": 0
                    },
                    {
                      "url": "cardinalityMax",
                      "valueInteger": 1
                    }
                  ]
                }
              ],
              "display": "Encounter[PV1].participant[1].individual(PractitionerRole.organziation.(Organization))",
              "dependsOn": [
                {
                  "property": "data-type-map",
                  "value": "XON[Organization]"
                }
              ]
            }
          ]
        }
      ]
    }
  ]
}
